{
  "type": "Feature",
  "properties": {
    "gn:admin1_code":"04",
    "gn:asciiname":"Ercan",
    "gn:country_code":"CY",
    "gn:dem":115,
    "gn:feature_class":"P",
    "gn:feature_code":"PPLL",
    "gn:name":"Ercan",
    "gn:population":0,
    "gn:timezone":"Asia/Nicosia",
    "iso:country":"CY",
    "name:eng_x_preferred":[
        "Ercan"
    ],
    "name:tur_x_preferred":[
        "Ercan"
    ],
    "wof:name":"Ercan",
    "wof:placetype":"locality"
},
  "geometry": {"coordinates":[33.4986,35.16034000000001],"type":"Point"}
}