{
  "type": "Feature",
  "properties": {
    "iso:country":"CY",
    "name:bul_x_preferred":[
        "\u041b\u0435\u043c\u0431\u0430"
    ],
    "name:ceb_x_preferred":[
        "L\u00e9mpa"
    ],
    "name:deu_x_preferred":[
        "Lemba"
    ],
    "name:ell_x_preferred":[
        "L\u00e9mpa"
    ],
    "name:ell_x_variant":[
        "\u039b\u03ad\u03bc\u03c0\u03b1"
    ],
    "name:eng_x_preferred":[
        "Lempa"
    ],
    "name:fra_x_preferred":[
        "L\u00e9mpa"
    ],
    "name:hye_x_preferred":[
        "\u053c\u0565\u0574\u057a\u0561"
    ],
    "name:nld_x_preferred":[
        "Lempa"
    ],
    "name:pol_x_preferred":[
        "Lemba"
    ],
    "name:swe_x_preferred":[
        "L\u00e9mpa"
    ],
    "name:und_x_variant":[
        "\u00c7iral\u0131"
    ],
    "name:urd_x_preferred":[
        "\u0644\u06cc\u0645\u067e\u0627"
    ],
    "qs:a0":"\u039a\u03cd\u03c0\u03c1\u03bf\u03c2",
    "qs:a1":"*\u03a0\u03ac\u03c6\u03bf\u03c2",
    "qs:a1_alt":"Pafos",
    "qs:a1r":"0",
    "qs:adm0":"\u039a\u03cd\u03c0\u03c1\u03bf\u03c2",
    "qs:la_lc":"*",
    "qs:level":"locality",
    "qs:loc":"\u039b\u03ad\u03bc\u03c0\u03b1",
    "qs:loc_alt":"Lempa",
    "qs:pop":0,
    "qs:type":"buffered point",
    "wd:wordcount":600,
    "wof:name":"\u039b\u03ad\u03bc\u03c0\u03b1",
    "wof:placetype":"locality"
},
  "geometry": {"coordinates":[32.413531,34.813021],"type":"Point"}
}