{
  "type": "Feature",
  "properties": {
    "gn:admin1_code":"06",
    "gn:asciiname":"Moro Nero",
    "gn:country_code":"CY",
    "gn:dem":215,
    "gn:feature_class":"P",
    "gn:feature_code":"PPL",
    "gn:name":"Mor\u00f3 Ner\u00f3",
    "gn:population":0,
    "gn:timezone":"Asia/Nicosia",
    "iso:country":"CY",
    "name:ell_x_preferred":[
        "Mor\u00f3 Ner\u00f3"
    ],
    "name:ell_x_variant":[
        "\u039c\u03c9\u03c1\u03cc \u039d\u03b5\u03c1\u03cc"
    ],
    "name:und_x_variant":[
        "Moron Nero",
        "K\u00fc\u00e7\u00fcksu",
        "Moronero"
    ],
    "wof:name":"Moro Nero",
    "wof:placetype":"locality"
},
  "geometry": {"coordinates":[32.52589,34.81298],"type":"Point"}
}