{
  "type": "Feature",
  "properties": {
    "gn:population":6,
    "iso:country":"CY",
    "name:bul_x_preferred":[
        "\u0410\u043d\u0430\u0434\u0438\u0443"
    ],
    "name:ell_x_preferred":[
        "\u0391\u03bd\u03b1\u03b4\u03b9\u03bf\u03cd"
    ],
    "name:ell_x_variant":[
        "Anadio\u00fa"
    ],
    "name:eng_x_preferred":[
        "Anadhiou"
    ],
    "name:eng_x_variant":[
        "Anadhyou",
        "Anatyu"
    ],
    "name:fas_x_preferred":[
        "\u0627\u0646\u0627\u062f\u0647\u06cc\u0648"
    ],
    "name:hye_x_preferred":[
        "\u0531\u0576\u0561\u0564\u056b\u0578\u0582"
    ],
    "name:nld_x_preferred":[
        "Anadhiou"
    ],
    "name:pol_x_preferred":[
        "Anadiu"
    ],
    "name:und_x_colloquial":[
        "Goermeli",
        "Gormeli"
    ],
    "name:und_x_variant":[
        "G\u00f6rmeli"
    ],
    "name:urd_x_preferred":[
        "\u0622\u0646\u0627\u062f\u06cc\u0648"
    ],
    "qs:a0":"\u039a\u03cd\u03c0\u03c1\u03bf\u03c2",
    "qs:a1":"*\u03a0\u03ac\u03c6\u03bf\u03c2",
    "qs:a1_alt":"Pafos",
    "qs:a1r":"0",
    "qs:adm0":"\u039a\u03cd\u03c0\u03c1\u03bf\u03c2",
    "qs:la_lc":"*",
    "qs:level":"locality",
    "qs:loc":"\u0391\u03bd\u03b1\u03b4\u03b9\u03bf\u03cd",
    "qs:loc_alt":"Anadiou",
    "qs:pop":0,
    "qs:type":"buffered point",
    "wd:wordcount":24,
    "wof:lang":[
        "eng"
    ],
    "wof:name":"\u0391\u03bd\u03b1\u03b4\u03b9\u03bf\u03cd",
    "wof:placetype":"locality",
    "wof:population":6
},
  "geometry": {"coordinates":[32.566311,34.944145],"type":"Point"}
}