{
  "type": "Feature",
  "properties": {
    "gn:population":66,
    "iso:country":"CY",
    "name:bul_x_preferred":[
        "\u041a\u0430\u0442\u043e \u041c\u0438\u043b\u043e\u0441"
    ],
    "name:dut_x_preferred":[
        "Kato Mylos"
    ],
    "name:ell_x_preferred":[
        "\u039a\u03ac\u03c4\u03c9 \u039c\u03cd\u03bb\u03bf\u03c2"
    ],
    "name:ell_x_variant":[
        "K\u00e1to M\u00fdlos"
    ],
    "name:eng_x_preferred":[
        "Kato Mylos"
    ],
    "name:eng_x_variant":[
        "Mylos",
        "Mylos Kato"
    ],
    "name:gre_x_preferred":[
        "\u039a\u03ac\u03c4\u03c9 \u039c\u03cd\u03bb\u03bf\u03c2"
    ],
    "name:pol_x_preferred":[
        "Kato Milos"
    ],
    "name:unk_x_variant":[
        "Mylos"
    ],
    "qs:a0":"\u039a\u03cd\u03c0\u03c1\u03bf\u03c2",
    "qs:a1":"*\u039b\u03b5\u03bc\u03b5\u03c3\u03cc\u03c2",
    "qs:a1_alt":"Lemesos",
    "qs:a1r":"0",
    "qs:adm0":"\u039a\u03cd\u03c0\u03c1\u03bf\u03c2",
    "qs:la_lc":"*",
    "qs:level":"locality",
    "qs:loc":"\u039a\u03ac\u03c4\u03c9 \u039c\u03cd\u03bb\u03bf\u03c2",
    "qs:loc_alt":"Kato Mylos",
    "qs:pop":0,
    "qs:type":"buffered point",
    "wd:wordcount":20,
    "wof:lang":[
        "eng"
    ],
    "wof:name":"\u039a\u03ac\u03c4\u03c9 \u039c\u03cd\u03bb\u03bf\u03c2",
    "wof:placetype":"locality",
    "wof:population":66
},
  "geometry": {"coordinates":[33.006567,34.895325],"type":"Point"}
}