{
  "type": "Feature",
  "properties": {
    "gn:country":"CY",
    "gn:fcode":"PPL",
    "gn:population":55,
    "iso:country":"CY",
    "name:bul_x_preferred":[
        "\u041f\u0440\u0435\u0442\u043e\u0440\u0438"
    ],
    "name:ell_x_preferred":[
        "Prait\u00f3ri"
    ],
    "name:ell_x_variant":[
        "\u03a0\u03c1\u03b1\u03b9\u03c4\u03ce\u03c1\u03b9"
    ],
    "name:eng_x_preferred":[
        "Praitori"
    ],
    "name:fra_x_preferred":[
        "Pret\u00f3ri"
    ],
    "name:hye_x_preferred":[
        "\u054a\u0580\u0561\u056b\u057f\u0578\u0580\u056b"
    ],
    "name:nld_x_preferred":[
        "Praitori"
    ],
    "name:pol_x_preferred":[
        "Praitori"
    ],
    "name:pus_x_preferred":[
        "\u067e\u0631\u0627\u064a\u062a\u0648\u0631\u064a"
    ],
    "name:und_x_variant":[
        "Pr\u00e6tori"
    ],
    "name:urd_x_preferred":[
        "\u067e\u0631\u0627\u0626\u062a\u0648\u0631\u06cc"
    ],
    "qs_pg:aaroncc":"CY",
    "qs_pg:gn_country":"CY",
    "qs_pg:gn_fcode":"PPL",
    "qs_pg:gn_pop":55,
    "qs_pg:name":"Pretori",
    "qs_pg:name_adm0":"Cyprus",
    "qs_pg:name_adm1":"Paphos District",
    "qs_pg:photos_9r":0,
    "qs_pg:photos_sr":0,
    "qs_pg:pop_sr":1,
    "qs_pg:qs_pg_placetype":"locality",
    "qs_pg:qs_pg_placetype_gp":"Town",
    "qs_pg:woe_adm0":26812346,
    "woe:adm0_id":26812346,
    "woe:name_adm0":"Cyprus",
    "woe:name_adm1":"Paphos District",
    "woe:placetype":"Town",
    "wof:name":"Pretori",
    "wof:placetype":"locality",
    "wof:population":55
},
  "geometry": {"coordinates":[32.75,34.85],"type":"Point"}
}