{
  "type": "Feature",
  "properties": {
    "gn:admin1_code":"02",
    "gn:asciiname":"Gerontas",
    "gn:country_code":"CY",
    "gn:dem":58,
    "gn:feature_class":"P",
    "gn:feature_code":"PPL",
    "gn:name":"Gerontas",
    "gn:population":0,
    "gn:timezone":"Asia/Famagusta",
    "iso:country":"CY",
    "name:und_x_variant":[
        "Yerondas"
    ],
    "wof:name":"Gerontas",
    "wof:placetype":"locality"
},
  "geometry": {"coordinates":[33.03089,35.36449],"type":"Point"}
}