{
  "type": "Feature",
  "properties": {
    "gn:population":343,
    "iso:country":"CY",
    "name:bul_x_preferred":[
        "\u0415\u043f\u0442\u0430\u0433\u043e\u043d\u0438\u044f"
    ],
    "name:ceb_x_preferred":[
        "Eptag\u00f3neia"
    ],
    "name:ell_x_preferred":[
        "\u0395\u03c0\u03c4\u03b1\u03b3\u03ce\u03bd\u03b9\u03b1"
    ],
    "name:ell_x_variant":[
        "Eptag\u00f3neia",
        "\u0395\u03c0\u03c4\u03b1\u03b3\u03ce\u03bd\u03b5\u03b9\u03b1"
    ],
    "name:eng_x_preferred":[
        "Ephtagonia"
    ],
    "name:eng_x_variant":[
        "Eftagonya",
        "Eptagoneia",
        "Eptagonia"
    ],
    "name:nld_x_preferred":[
        "Eptagoneia"
    ],
    "name:pol_x_preferred":[
        "Eptagonia"
    ],
    "name:swe_x_preferred":[
        "Eptag\u00f3neia"
    ],
    "name:unk_x_variant":[
        "Eptagonia"
    ],
    "qs:a0":"\u039a\u03cd\u03c0\u03c1\u03bf\u03c2",
    "qs:a1":"*\u039b\u03b5\u03bc\u03b5\u03c3\u03cc\u03c2",
    "qs:a1_alt":"Lemesos",
    "qs:a1r":"0",
    "qs:adm0":"\u039a\u03cd\u03c0\u03c1\u03bf\u03c2",
    "qs:la_lc":"*",
    "qs:level":"locality",
    "qs:loc":"\u0395\u03c0\u03c4\u03b1\u03b3\u03ce\u03bd\u03b5\u03b9\u03b1",
    "qs:loc_alt":"Eptagoneia",
    "qs:pop":0,
    "qs:type":"buffered point",
    "wd:wordcount":74,
    "wof:lang":[
        "eng"
    ],
    "wof:name":"\u0395\u03c0\u03c4\u03b1\u03b3\u03ce\u03bd\u03b5\u03b9\u03b1",
    "wof:placetype":"locality",
    "wof:population":343
},
  "geometry": {"coordinates":[33.157532,34.847759],"type":"Point"}
}