{
  "type": "Feature",
  "properties": {
    "iso:country":"CY",
    "name:arm_x_preferred":[
        "\u054a\u0561\u0576\u0561\u0563\u0580\u0561"
    ],
    "name:bul_x_preferred":[
        "\u041f\u0430\u043d\u0430\u0433\u0440\u0430"
    ],
    "name:dut_x_preferred":[
        "Panagra"
    ],
    "name:ell_x_preferred":[
        "P\u00e1nagra"
    ],
    "name:ell_x_variant":[
        "\u03a0\u03ac\u03bd\u03b1\u03b3\u03c1\u03b1"
    ],
    "name:eng_x_preferred":[
        "Panagra"
    ],
    "name:gre_x_preferred":[
        "\u03a0\u03ac\u03bd\u03b1\u03b3\u03c1\u03b1"
    ],
    "name:und_x_colloquial":[
        "Gecitkoey",
        "Gecitkoy"
    ],
    "name:und_x_preferred":[
        "Panagra"
    ],
    "name:und_x_variant":[
        "Ge\u00e7itk\u00f6y"
    ],
    "name:unk_x_variant":[
        "Ge\u00e7itk\u00f6y"
    ],
    "qs:a0":"\u039a\u03cd\u03c0\u03c1\u03bf\u03c2",
    "qs:a1":"*\u039a\u03b5\u03c1\u03cd\u03bd\u03b5\u03b9\u03b1",
    "qs:a1_alt":"Keryneia",
    "qs:a1r":"0",
    "qs:adm0":"\u039a\u03cd\u03c0\u03c1\u03bf\u03c2",
    "qs:la_lc":"*",
    "qs:level":"locality",
    "qs:loc":"\u03a0\u03ac\u03bd\u03b1\u03b3\u03c1\u03b1",
    "qs:loc_alt":"Panagra",
    "qs:pop":0,
    "qs:type":"buffered point",
    "wof:lang":[
        "unk"
    ],
    "wof:name":"\u03a0\u03ac\u03bd\u03b1\u03b3\u03c1\u03b1",
    "wof:placetype":"locality"
},
  "geometry": {"coordinates":[33.068241,35.336506],"type":"Point"}
}