{
  "type": "Feature",
  "properties": {
    "gn:country":"CY",
    "gn:fcode":"PPL",
    "gn:population":115,
    "iso:country":"CY",
    "name:bul_x_preferred":[
        "\u041c\u0430\u0442\u0438\u043a\u043e\u043b\u043e\u043d\u0438"
    ],
    "name:ceb_x_preferred":[
        "Mathikol\u00f3ni"
    ],
    "name:ell_x_preferred":[
        "Mathikol\u00f3ni"
    ],
    "name:ell_x_variant":[
        "\u039c\u03b1\u03b8\u03b9\u03ba\u03bf\u03bb\u03ce\u03bd\u03b7"
    ],
    "name:eng_x_preferred":[
        "Mathikoloni"
    ],
    "name:fra_x_preferred":[
        "Mathikol\u00f3ni"
    ],
    "name:nld_x_preferred":[
        "Mathikoloni"
    ],
    "name:pol_x_preferred":[
        "Matikoloni"
    ],
    "name:swe_x_preferred":[
        "Mathikol\u00f3ni"
    ],
    "name:und_x_variant":[
        "Madikoloni"
    ],
    "qs_pg:aaroncc":"CY",
    "qs_pg:gn_country":"CY",
    "qs_pg:gn_fcode":"PPL",
    "qs_pg:gn_pop":115,
    "qs_pg:name":"Mathikoloni",
    "qs_pg:name_adm0":"Cyprus",
    "qs_pg:name_adm1":"Limassol District",
    "qs_pg:photos":281,
    "qs_pg:photos_1k":57,
    "qs_pg:photos_9k":1,
    "qs_pg:photos_9r":4,
    "qs_pg:photos_all":281,
    "qs_pg:photos_sr":5,
    "qs_pg:pop_sr":1,
    "qs_pg:qs_pg_placetype":"locality",
    "qs_pg:qs_pg_placetype_gp":"Town",
    "qs_pg:woe_adm0":26812346,
    "woe:adm0_id":26812346,
    "woe:name_adm0":"Cyprus",
    "woe:name_adm1":"Limassol District",
    "woe:placetype":"Town",
    "wof:name":"Mathikoloni",
    "wof:placetype":"locality",
    "wof:population":115
},
  "geometry": {"coordinates":[33.05,34.76667],"type":"Point"}
}