{
  "type": "Feature",
  "properties": {
    "gn:population":27,
    "iso:country":"CY",
    "name:bul_x_preferred":[
        "\u0410\u0440\u043c\u0438\u043d\u0443"
    ],
    "name:deu_x_preferred":[
        "Arminou"
    ],
    "name:ell_x_preferred":[
        "Arm\u00ednou"
    ],
    "name:ell_x_variant":[
        "\u0391\u03c1\u03bc\u03af\u03bd\u03bf\u03c5"
    ],
    "name:eng_x_preferred":[
        "Arminou"
    ],
    "name:fas_x_preferred":[
        "\u0627\u0631\u0645\u06cc\u0646\u0648"
    ],
    "name:fra_x_preferred":[
        "Arm\u00ednou"
    ],
    "name:hye_x_preferred":[
        "\u0531\u0580\u0574\u056b\u0576\u0578\u0582"
    ],
    "name:pol_x_preferred":[
        "Arminu"
    ],
    "name:urd_x_preferred":[
        "\u0622\u0631\u0645\u06cc\u0646\u0648"
    ],
    "qs:a0":"\u039a\u03cd\u03c0\u03c1\u03bf\u03c2",
    "qs:a1":"*\u03a0\u03ac\u03c6\u03bf\u03c2",
    "qs:a1_alt":"Pafos",
    "qs:a1r":"0",
    "qs:adm0":"\u039a\u03cd\u03c0\u03c1\u03bf\u03c2",
    "qs:la_lc":"*",
    "qs:level":"locality",
    "qs:loc":"\u0391\u03c1\u03bc\u03af\u03bd\u03bf\u03c5",
    "qs:loc_alt":"Arminou",
    "qs:pop":0,
    "qs:type":"buffered point",
    "wd:wordcount":443,
    "wof:lang":[
        "eng"
    ],
    "wof:name":"\u0391\u03c1\u03bc\u03af\u03bd\u03bf\u03c5",
    "wof:placetype":"locality",
    "wof:population":27
},
  "geometry": {"coordinates":[32.720196,34.861988],"type":"Point"}
}