{
  "type": "Feature",
  "properties": {
    "iso:country":"CY",
    "name:arm_x_preferred":[
        "\u0556\u056b\u0576\u056b\u056f\u0561\u057d"
    ],
    "name:bul_x_preferred":[
        "\u0424\u0438\u043d\u0438\u043a\u0430\u0441"
    ],
    "name:dut_x_preferred":[
        "Phinikas"
    ],
    "name:ell_x_preferred":[
        "Fo\u00ednikas"
    ],
    "name:ell_x_variant":[
        "\u03a6\u03bf\u03af\u03bd\u03b9\u03ba\u03b1\u03c2"
    ],
    "name:eng_x_preferred":[
        "Phinikas"
    ],
    "name:eng_x_variant":[
        "Finike"
    ],
    "name:gre_x_preferred":[
        "\u03a6\u03bf\u03af\u03bd\u03b9\u03ba\u03b1\u03c2 \u03a0\u03ac\u03c6\u03bf\u03c5"
    ],
    "name:hye_x_preferred":[
        "\u0556\u056b\u0576\u056b\u056f\u0561\u057d"
    ],
    "name:pol_x_preferred":[
        "Finikas"
    ],
    "name:unk_x_variant":[
        "Finikas"
    ],
    "qs:a0":"\u039a\u03cd\u03c0\u03c1\u03bf\u03c2",
    "qs:a1":"*\u03a0\u03ac\u03c6\u03bf\u03c2",
    "qs:a1_alt":"Pafos",
    "qs:a1r":"0",
    "qs:adm0":"\u039a\u03cd\u03c0\u03c1\u03bf\u03c2",
    "qs:la_lc":"*",
    "qs:level":"locality",
    "qs:loc":"\u03a6\u03bf\u03af\u03bd\u03b9\u03ba\u03b1\u03c2",
    "qs:loc_alt":"Foinikas",
    "qs:pop":0,
    "qs:type":"buffered point",
    "wd:wordcount":37,
    "wof:lang":[
        "eng"
    ],
    "wof:name":"\u03a6\u03bf\u03af\u03bd\u03b9\u03ba\u03b1\u03c2",
    "wof:placetype":"locality"
},
  "geometry": {"coordinates":[32.568565,34.753322],"type":"Point"}
}