{
  "type": "Feature",
  "properties": {
    "gn:population":185,
    "iso:country":"CY",
    "name:arm_x_preferred":[
        "\u054f\u0565\u056c\u0565\u057f\u0580\u0561"
    ],
    "name:bul_x_preferred":[
        "\u0422\u0435\u043b\u0435\u0442\u0440\u0430"
    ],
    "name:ceb_x_preferred":[
        "Thel\u00e9tra"
    ],
    "name:dut_x_preferred":[
        "Theletra"
    ],
    "name:ell_x_preferred":[
        "Thel\u00e9tra"
    ],
    "name:ell_x_variant":[
        "\u0398\u03b5\u03bb\u03ad\u03c4\u03c1\u03b1"
    ],
    "name:eng_x_preferred":[
        "Theletra"
    ],
    "name:gre_x_preferred":[
        "\u0398\u03b5\u03bb\u03ad\u03c4\u03c1\u03b1"
    ],
    "name:hye_x_preferred":[
        "\u054f\u0565\u056c\u0565\u057f\u0580\u0561"
    ],
    "name:pol_x_preferred":[
        "Teletra"
    ],
    "name:swe_x_preferred":[
        "Thel\u00e9tra"
    ],
    "name:unk_x_variant":[
        "Teletra"
    ],
    "qs:a0":"\u039a\u03cd\u03c0\u03c1\u03bf\u03c2",
    "qs:a1":"*\u03a0\u03ac\u03c6\u03bf\u03c2",
    "qs:a1_alt":"Pafos",
    "qs:a1r":"0",
    "qs:adm0":"\u039a\u03cd\u03c0\u03c1\u03bf\u03c2",
    "qs:la_lc":"*",
    "qs:level":"locality",
    "qs:loc":"\u0398\u03b5\u03bb\u03ad\u03c4\u03c1\u03b1",
    "qs:loc_alt":"Theletra",
    "qs:pop":0,
    "qs:type":"buffered point",
    "wd:wordcount":74,
    "wof:lang":[
        "eng"
    ],
    "wof:name":"\u0398\u03b5\u03bb\u03ad\u03c4\u03c1\u03b1",
    "wof:placetype":"locality",
    "wof:population":185
},
  "geometry": {"coordinates":[32.45567,34.912884],"type":"Point"}
}