{
  "type": "Feature",
  "properties": {
    "gn:admin1_code":"04",
    "gn:asciiname":"Kato Koutrafas",
    "gn:country_code":"CY",
    "gn:dem":193,
    "gn:feature_class":"P",
    "gn:feature_code":"PPL",
    "gn:name":"K\u00e1to Koutraf\u00e1s",
    "gn:population":0,
    "gn:timezone":"Asia/Nicosia",
    "iso:country":"CY",
    "name:ell_x_preferred":[
        "K\u00e1to Koutraf\u00e1s"
    ],
    "name:ell_x_variant":[
        "\u039a\u03ac\u03c4\u03c9 \u039a\u03bf\u03c5\u03c4\u03c1\u03b1\u03c6\u03ac\u03c2"
    ],
    "name:pol_x_preferred":[
        "Kato Kutrafas"
    ],
    "name:tur_x_preferred":[
        "A\u015fa\u011f\u0131 Kurtbo\u011fan"
    ],
    "name:und_x_variant":[
        "Koutraphas",
        "Kato Koutrapha",
        "Koutrapha",
        "A\u015fa\u011f\u0131 Kurtbo\u011fan",
        "Kato Kutrafa",
        "Kato Koutraphas"
    ],
    "name:urd_x_preferred":[
        "\u06a9\u0627\u062a\u0648 \u06a9\u0648\u062a\u0631\u0627\u0641\u0627\u0633"
    ],
    "wof:name":"Kato Koutrafas",
    "wof:placetype":"locality"
},
  "geometry": {"coordinates":[32.9776,35.10277],"type":"Point"}
}