{
  "type": "Feature",
  "properties": {
    "gn:population":272,
    "iso:country":"CY",
    "name:bul_x_preferred":[
        "\u041b\u0438\u043c\u043d\u0430\u0442\u0438\u0441"
    ],
    "name:ceb_x_preferred":[
        "Limn\u00e1tis"
    ],
    "name:ell_x_preferred":[
        "\u039b\u03b9\u03bc\u03bd\u03ac\u03c4\u03b7\u03c2"
    ],
    "name:ell_x_variant":[
        "Limn\u00e1tis"
    ],
    "name:eng_x_preferred":[
        "Limnatis"
    ],
    "name:eng_x_variant":[
        "Linnatis"
    ],
    "name:fra_x_preferred":[
        "Limn\u00e1tis"
    ],
    "name:nld_x_preferred":[
        "Limnatis"
    ],
    "name:pol_x_preferred":[
        "Limnatis"
    ],
    "name:swe_x_preferred":[
        "Limn\u00e1tis"
    ],
    "qs:a0":"\u039a\u03cd\u03c0\u03c1\u03bf\u03c2",
    "qs:a1":"*\u039b\u03b5\u03bc\u03b5\u03c3\u03cc\u03c2",
    "qs:a1_alt":"Lemesos",
    "qs:a1r":"0",
    "qs:adm0":"\u039a\u03cd\u03c0\u03c1\u03bf\u03c2",
    "qs:la_lc":"*",
    "qs:level":"locality",
    "qs:loc":"\u039b\u03b9\u03bc\u03bd\u03ac\u03c4\u03b7\u03c2",
    "qs:loc_alt":"Limnatis",
    "qs:pop":0,
    "qs:type":"buffered point",
    "wd:wordcount":544,
    "wof:lang":[
        "eng"
    ],
    "wof:name":"\u039b\u03b9\u03bc\u03bd\u03ac\u03c4\u03b7\u03c2",
    "wof:placetype":"locality",
    "wof:population":272
},
  "geometry": {"coordinates":[32.948399,34.815113],"type":"Point"}
}