{
  "type": "Feature",
  "properties": {
    "gn:population":110,
    "iso:country":"CY",
    "name:bul_x_preferred":[
        "\u041d\u0438\u043a\u043e\u043a\u043b\u0438\u044f"
    ],
    "name:ceb_x_preferred":[
        "Nik\u00f3kleia"
    ],
    "name:ell_x_preferred":[
        "Nik\u00f3kleia"
    ],
    "name:ell_x_variant":[
        "\u039d\u03b9\u03ba\u03cc\u03ba\u03bb\u03b5\u03b9\u03b1"
    ],
    "name:eng_x_preferred":[
        "Nikoklia"
    ],
    "name:eng_x_variant":[
        "Nikokleia",
        "Nikolia"
    ],
    "name:hye_x_preferred":[
        "\u0546\u056b\u056f\u0578\u056f\u056c\u056b\u0561"
    ],
    "name:nld_x_preferred":[
        "Nikokleia"
    ],
    "name:pol_x_preferred":[
        "Nikoklia"
    ],
    "name:swe_x_preferred":[
        "Nik\u00f3kleia"
    ],
    "name:unk_x_variant":[
        "Nikoklo"
    ],
    "qs:a0":"\u039a\u03cd\u03c0\u03c1\u03bf\u03c2",
    "qs:a1":"*\u03a0\u03ac\u03c6\u03bf\u03c2",
    "qs:a1_alt":"Pafos",
    "qs:a1r":"0",
    "qs:adm0":"\u039a\u03cd\u03c0\u03c1\u03bf\u03c2",
    "qs:la_lc":"*",
    "qs:level":"locality",
    "qs:loc":"\u039d\u03b9\u03ba\u03cc\u03ba\u03bb\u03b5\u03b9\u03b1",
    "qs:loc_alt":"Nikokleia",
    "qs:pop":0,
    "qs:type":"buffered point",
    "wd:wordcount":20,
    "wof:lang":[
        "eng"
    ],
    "wof:name":"\u039d\u03b9\u03ba\u03cc\u03ba\u03bb\u03b5\u03b9\u03b1",
    "wof:placetype":"locality",
    "wof:population":110
},
  "geometry": {"coordinates":[32.575408,34.729138],"type":"Point"}
}