{
  "type": "Feature",
  "properties": {
    "gn:population":59,
    "iso:country":"CY",
    "name:bul_x_preferred":[
        "\u041c\u0435\u043b\u0438\u043d\u0438"
    ],
    "name:ell_x_preferred":[
        "\u039c\u03b5\u03bb\u03af\u03bd\u03b7 \u039b\u03ac\u03c1\u03bd\u03b1\u03ba\u03b1\u03c2"
    ],
    "name:ell_x_variant":[
        "Mel\u00edni",
        "\u039c\u03b5\u03bb\u03af\u03bd\u03b7"
    ],
    "name:eng_x_preferred":[
        "Melini"
    ],
    "name:fas_x_preferred":[
        "\u0645\u0644\u06cc\u0646\u06cc"
    ],
    "name:hye_x_preferred":[
        "\u0544\u0565\u056c\u056b\u0576\u056b"
    ],
    "name:nld_x_preferred":[
        "Melini"
    ],
    "name:pol_x_preferred":[
        "Melini"
    ],
    "qs:a0":"\u039a\u03cd\u03c0\u03c1\u03bf\u03c2",
    "qs:a1":"*\u039b\u03ac\u03c1\u03bd\u03b1\u03ba\u03b1",
    "qs:a1_alt":"Larnaka",
    "qs:a1r":"0",
    "qs:adm0":"\u039a\u03cd\u03c0\u03c1\u03bf\u03c2",
    "qs:la_lc":"*",
    "qs:level":"locality",
    "qs:loc":"\u039c\u03b5\u03bb\u03af\u03bd\u03b7",
    "qs:loc_alt":"Melini",
    "qs:pop":0,
    "qs:type":"buffered point",
    "wd:wordcount":56,
    "wof:name":"\u039c\u03b5\u03bb\u03af\u03bd\u03b7",
    "wof:placetype":"locality",
    "wof:population":59
},
  "geometry": {"coordinates":[33.158088,34.867447],"type":"Point"}
}