{
  "type": "Feature",
  "properties": {
    "gn:population":85,
    "iso:country":"CY",
    "name:bul_x_preferred":[
        "\u0413\u0435\u0440\u0430\u0441\u0430"
    ],
    "name:deu_x_preferred":[
        "Gerasa"
    ],
    "name:ell_x_preferred":[
        "\u0393\u03b5\u03c1\u03ac\u03c3\u03b1"
    ],
    "name:ell_x_variant":[
        "Ger\u00e1sa"
    ],
    "name:eng_x_preferred":[
        "Yerasa"
    ],
    "name:eng_x_variant":[
        "Gerasa"
    ],
    "name:fra_x_preferred":[
        "Ger\u00e1sa"
    ],
    "name:hun_x_preferred":[
        "Jer\u00e1sza"
    ],
    "name:nld_x_preferred":[
        "Gerasa"
    ],
    "name:pol_x_preferred":[
        "Jerasa"
    ],
    "qs:a0":"\u039a\u03cd\u03c0\u03c1\u03bf\u03c2",
    "qs:a1":"*\u039b\u03b5\u03bc\u03b5\u03c3\u03cc\u03c2",
    "qs:a1_alt":"Lemesos",
    "qs:a1r":"0",
    "qs:adm0":"\u039a\u03cd\u03c0\u03c1\u03bf\u03c2",
    "qs:la_lc":"*",
    "qs:level":"locality",
    "qs:loc":"\u0393\u03b5\u03c1\u03ac\u03c3\u03b1",
    "qs:loc_alt":"Gerasa",
    "qs:pop":0,
    "qs:type":"buffered point",
    "wd:wordcount":20,
    "wof:lang":[
        "eng"
    ],
    "wof:name":"\u0393\u03b5\u03c1\u03ac\u03c3\u03b1",
    "wof:placetype":"locality",
    "wof:population":85
},
  "geometry": {"coordinates":[32.998486,34.802651],"type":"Point"}
}