{
  "type": "Feature",
  "properties": {
    "gn:population":173,
    "iso:country":"CY",
    "name:bul_x_preferred":[
        "\u041a\u043e\u0440\u0444\u0438"
    ],
    "name:ceb_x_preferred":[
        "Korf\u00ed"
    ],
    "name:ell_x_preferred":[
        "\u039a\u03bf\u03c1\u03c6\u03ae"
    ],
    "name:ell_x_variant":[
        "Korf\u00ed"
    ],
    "name:eng_x_preferred":[
        "Korphi"
    ],
    "name:eng_x_variant":[
        "Gorfi",
        "Korfi"
    ],
    "name:fra_x_preferred":[
        "Korf\u00ed"
    ],
    "name:nld_x_preferred":[
        "Korfi"
    ],
    "name:pol_x_preferred":[
        "Korfi"
    ],
    "name:swe_x_preferred":[
        "Korf\u00ed"
    ],
    "name:unk_x_variant":[
        "Yeni Korfi"
    ],
    "qs:a0":"\u039a\u03cd\u03c0\u03c1\u03bf\u03c2",
    "qs:a1":"*\u039b\u03b5\u03bc\u03b5\u03c3\u03cc\u03c2",
    "qs:a1_alt":"Lemesos",
    "qs:a1r":"0",
    "qs:adm0":"\u039a\u03cd\u03c0\u03c1\u03bf\u03c2",
    "qs:la_lc":"*",
    "qs:level":"locality",
    "qs:loc":"\u039a\u03bf\u03c1\u03c6\u03ae",
    "qs:loc_alt":"Korfi",
    "qs:pop":0,
    "qs:type":"buffered point",
    "wd:wordcount":24,
    "wof:lang":[
        "eng"
    ],
    "wof:name":"\u039a\u03bf\u03c1\u03c6\u03ae",
    "wof:placetype":"locality",
    "wof:population":173
},
  "geometry": {"coordinates":[32.971211,34.806595],"type":"Point"}
}