{
  "type": "Feature",
  "properties": {
    "gn:admin1_code":"06",
    "gn:asciiname":"Anavargos",
    "gn:country_code":"CY",
    "gn:dem":189,
    "gn:feature_class":"P",
    "gn:feature_code":"PPL",
    "gn:name":"Anavargos",
    "gn:population":0,
    "gn:timezone":"Asia/Nicosia",
    "iso:country":"CY",
    "name:und_x_variant":[
        "Anavargo",
        "Anavargos"
    ],
    "wof:name":"Anavargos",
    "wof:placetype":"locality"
},
  "geometry": {"coordinates":[32.45151,34.79464],"type":"Point"}
}