{
  "type": "Feature",
  "properties": {
    "gn:admin1_code":"04",
    "gn:asciiname":"Apliki",
    "gn:country_code":"CY",
    "gn:dem":153,
    "gn:feature_class":"P",
    "gn:feature_code":"PPL",
    "gn:name":"Apl\u00edki",
    "gn:population":0,
    "gn:timezone":"Asia/Nicosia",
    "iso:country":"CY",
    "name:deu_x_preferred":[
        "Apliki"
    ],
    "name:ell_x_preferred":[
        "Apl\u00edki"
    ],
    "name:ell_x_variant":[
        "\u0391\u03c0\u03bb\u03af\u03ba\u03b9"
    ],
    "name:hye_x_preferred":[
        "\u0531\u057a\u056c\u056b\u056f\u056b"
    ],
    "name:pol_x_preferred":[
        "Apliki"
    ],
    "name:tur_x_preferred":[
        "Apl\u0131\u00e7"
    ],
    "name:und_x_variant":[
        "Apli\u00e7",
        "Ali\u00e7lar"
    ],
    "name:urd_x_preferred":[
        "\u0627\u067e\u0644\u06cc\u06a9\u06cc"
    ],
    "wof:name":"Apliki",
    "wof:placetype":"locality"
},
  "geometry": {"coordinates":[32.84907,35.10041],"type":"Point"}
}