{
  "type": "Feature",
  "properties": {
    "iso:country":"CY",
    "name:ell_x_preferred":[
        "Ki\u00f3mourtzou"
    ],
    "name:ell_x_variant":[
        "\u039a\u03b9\u03cc\u03bc\u03bf\u03c5\u03c1\u03c4\u03b6\u03bf\u03c5"
    ],
    "name:und_x_variant":[
        "K\u00f6m\u00fcrc\u00fc"
    ],
    "qs:a0":"\u039a\u03cd\u03c0\u03c1\u03bf\u03c2",
    "qs:a1":"*\u039a\u03b5\u03c1\u03cd\u03bd\u03b5\u03b9\u03b1",
    "qs:a1_alt":"Keryneia",
    "qs:a1r":"0",
    "qs:adm0":"\u039a\u03cd\u03c0\u03c1\u03bf\u03c2",
    "qs:la_lc":"*",
    "qs:level":"locality",
    "qs:loc":"\u039a\u03b9\u03bf\u03bc\u03bf\u03c5\u03c1\u03c4\u03b6\u03bf\u03cd",
    "qs:loc_alt":"Kiomourtzou",
    "qs:pop":0,
    "qs:type":"buffered point",
    "wof:name":"\u039a\u03b9\u03bf\u03bc\u03bf\u03c5\u03c1\u03c4\u03b6\u03bf\u03cd",
    "wof:placetype":"locality"
},
  "geometry": {"coordinates":[33.256233,35.293052],"type":"Point"}
}