{
  "type": "Feature",
  "properties": {
    "gn:population":52,
    "iso:country":"CY",
    "name:bul_x_preferred":[
        "\u041c\u0435\u0441\u0430\u043d\u0430"
    ],
    "name:ell_x_preferred":[
        "M\u00e9sana"
    ],
    "name:ell_x_variant":[
        "\u039c\u03ad\u03c3\u03b1\u03bd\u03b1"
    ],
    "name:eng_x_preferred":[
        "Mesana"
    ],
    "name:hye_x_preferred":[
        "\u0544\u0565\u057d\u0561\u0576\u0561"
    ],
    "name:nld_x_preferred":[
        "Mesana"
    ],
    "name:pol_x_preferred":[
        "Mesana"
    ],
    "name:urd_x_preferred":[
        "\u0645\u06cc\u0633\u0627\u0646\u0627"
    ],
    "qs:a0":"\u039a\u03cd\u03c0\u03c1\u03bf\u03c2",
    "qs:a1":"*\u03a0\u03ac\u03c6\u03bf\u03c2",
    "qs:a1_alt":"Pafos",
    "qs:a1r":"0",
    "qs:adm0":"\u039a\u03cd\u03c0\u03c1\u03bf\u03c2",
    "qs:la_lc":"*",
    "qs:level":"locality",
    "qs:loc":"\u039c\u03ad\u03c3\u03b1\u03bd\u03b1",
    "qs:loc_alt":"Mesana",
    "qs:pop":0,
    "qs:type":"buffered point",
    "wd:wordcount":20,
    "wof:lang":[
        "eng"
    ],
    "wof:name":"\u039c\u03ad\u03c3\u03b1\u03bd\u03b1",
    "wof:placetype":"locality",
    "wof:population":52
},
  "geometry": {"coordinates":[32.706997,34.848809],"type":"Point"}
}