{
  "type": "Feature",
  "properties": {
    "gn:population":207,
    "iso:country":"CY",
    "name:arm_x_preferred":[
        "\u0536\u0578\u0583\u056b\u056b"
    ],
    "name:bul_x_preferred":[
        "\u0417\u043e\u043e\u043f\u0438\u0433\u0438"
    ],
    "name:ceb_x_preferred":[
        "Zoopig\u00ed"
    ],
    "name:dut_x_preferred":[
        "Zoopigi"
    ],
    "name:ell_x_preferred":[
        "\u0396\u03c9\u03bf\u03c0\u03b7\u03b3\u03ae"
    ],
    "name:ell_x_variant":[
        "Zoopig\u00ed"
    ],
    "name:eng_x_preferred":[
        "Zoopiyi"
    ],
    "name:eng_x_variant":[
        "Zoopigi"
    ],
    "name:gre_x_preferred":[
        "\u0396\u03c9\u03bf\u03c0\u03b7\u03b3\u03ae"
    ],
    "name:hye_x_preferred":[
        "\u0536\u0578\u0583\u056b\u056b"
    ],
    "name:pol_x_preferred":[
        "Zoopiji"
    ],
    "name:swe_x_preferred":[
        "Zoopig\u00ed"
    ],
    "name:und_x_colloquial":[
        "Zoobiyi"
    ],
    "name:und_x_variant":[
        "Zoobiy\u00ed"
    ],
    "name:unk_x_variant":[
        "Zoobiy\u00ed"
    ],
    "qs:a0":"\u039a\u03cd\u03c0\u03c1\u03bf\u03c2",
    "qs:a1":"*\u039b\u03b5\u03bc\u03b5\u03c3\u03cc\u03c2",
    "qs:a1_alt":"Lemesos",
    "qs:a1r":"0",
    "qs:adm0":"\u039a\u03cd\u03c0\u03c1\u03bf\u03c2",
    "qs:la_lc":"*",
    "qs:level":"locality",
    "qs:loc":"\u0396\u03c9\u03bf\u03c0\u03b7\u03b3\u03ae",
    "qs:loc_alt":"Zoopigi",
    "qs:pop":0,
    "qs:type":"buffered point",
    "wd:wordcount":21,
    "wof:lang":[
        "eng"
    ],
    "wof:name":"\u0396\u03c9\u03bf\u03c0\u03b7\u03b3\u03ae",
    "wof:placetype":"locality",
    "wof:population":207
},
  "geometry": {"coordinates":[33.015327,34.863453],"type":"Point"}
}