{
  "type": "Feature",
  "properties": {
    "gn:gn_country":"CY",
    "gn:gn_fcode":"PPL",
    "gn:gn_pop":0,
    "iso:country":"CY",
    "name:bul_x_preferred":[
        "\u0410\u0433\u0438\u043e\u0441 \u0410\u043c\u0432\u0440\u043e\u0441\u0438\u043e\u0441"
    ],
    "name:ell_x_preferred":[
        "\u00c1gios Amvr\u00f3sios"
    ],
    "name:ell_x_variant":[
        "\u0386\u03b3\u03b9\u03bf\u03c2 \u0391\u03bc\u03b2\u03c1\u03cc\u03c3\u03b9\u03bf\u03c2",
        "\u0386\u03b3\u03b9\u03bf\u03c2 \u0391\u03bc\u03b2\u03c1\u03cc\u03c3\u03b9\u03bf\u03c2 \u039a\u03b5\u03c1\u03cd\u03bd\u03b5\u03b9\u03b1\u03c2"
    ],
    "name:eng_x_preferred":[
        "Agios Amvrosios"
    ],
    "name:fas_x_preferred":[
        "\u0627\u06af\u06cc\u0648\u0627\u0633 \u0627\u0645\u0648\u0631\u0648\u0633\u06cc\u0648\u0633\u060c \u06a9\u06cc\u0631\u0646\u06cc\u0627"
    ],
    "name:hye_x_preferred":[
        "\u0531\u0575\u0578\u057d \u0531\u0574\u057e\u0580\u0578\u057d\u056b\u0578\u057d"
    ],
    "name:nld_x_preferred":[
        "Esentepe"
    ],
    "name:nno_x_preferred":[
        "\u00c1jos Amvr\u00f3sios"
    ],
    "name:pol_x_preferred":[
        "Ajos Amwrosios"
    ],
    "name:swe_x_preferred":[
        "\u00c1gios Amvr\u00f3sios"
    ],
    "name:tur_x_preferred":[
        "Esentepe"
    ],
    "name:unk_x_variant":[
        "Saint Amvrosios"
    ],
    "name:urd_x_preferred":[
        "\u0627\u06af\u06cc\u0648\u0627\u0633 \u0627\u0645\u0648\u0631\u0648\u0633\u06cc\u0648\u0633\u060c \u06a9\u06cc\u0631\u0646\u06cc\u0627"
    ],
    "qs_pg:aaroncc":"CY",
    "qs_pg:gn_country":"CY",
    "qs_pg:gn_fcode":"PPL",
    "qs_pg:gn_pop":0,
    "qs_pg:name":"Agios Amvrosios",
    "qs_pg:name_adm0":"Cyprus",
    "qs_pg:name_adm1":"Kyrenia District",
    "qs_pg:photos":127,
    "qs_pg:photos_1k":26,
    "qs_pg:photos_9k":1,
    "qs_pg:photos_9r":3,
    "qs_pg:photos_all":127,
    "qs_pg:photos_sr":3,
    "qs_pg:pop_sr":4,
    "qs_pg:qs_pg_placetype":"locality",
    "qs_pg:qs_pg_placetype_gp":"Town",
    "qs_pg:woe_adm0":26812346,
    "woe:adm0_id":26812346,
    "woe:name_adm0":"Cyprus",
    "woe:name_adm1":"Kyrenia District",
    "woe:placetype":"Town",
    "wof:name":"Agios Amvrosios",
    "wof:placetype":"locality"
},
  "geometry": {"coordinates":[33.57917,35.34167],"type":"Point"}
}