{
  "type": "Feature",
  "properties": {
    "gn:population":115,
    "iso:country":"CY",
    "name:bul_x_preferred":[
        "\u041c\u0430\u0442\u0438\u043a\u043e\u043b\u043e\u043d\u0438"
    ],
    "name:ceb_x_preferred":[
        "Mathikol\u00f3ni"
    ],
    "name:ell_x_preferred":[
        "\u039c\u03b1\u03b8\u03b7\u03ba\u03bf\u03bb\u03ce\u03bd\u03b7"
    ],
    "name:ell_x_variant":[
        "Mathikol\u00f3ni",
        "\u039c\u03b1\u03b8\u03b9\u03ba\u03bf\u03bb\u03ce\u03bd\u03b7"
    ],
    "name:eng_x_preferred":[
        "Mathikoloni"
    ],
    "name:fra_x_preferred":[
        "Mathikol\u00f3ni"
    ],
    "name:nld_x_preferred":[
        "Mathikoloni"
    ],
    "name:pol_x_preferred":[
        "Matikoloni"
    ],
    "name:swe_x_preferred":[
        "Mathikol\u00f3ni"
    ],
    "name:und_x_variant":[
        "Madikoloni"
    ],
    "qs:a0":"\u039a\u03cd\u03c0\u03c1\u03bf\u03c2",
    "qs:a1":"*\u039b\u03b5\u03bc\u03b5\u03c3\u03cc\u03c2",
    "qs:a1_alt":"Lemesos",
    "qs:a1r":"0",
    "qs:adm0":"\u039a\u03cd\u03c0\u03c1\u03bf\u03c2",
    "qs:la_lc":"*",
    "qs:level":"locality",
    "qs:loc":"\u039c\u03b1\u03b8\u03b9\u03ba\u03bf\u03bb\u03ce\u03bd\u03b7",
    "qs:loc_alt":"Mathikoloni",
    "qs:pop":0,
    "qs:type":"buffered point",
    "wd:wordcount":20,
    "wof:name":"\u039c\u03b1\u03b8\u03b9\u03ba\u03bf\u03bb\u03ce\u03bd\u03b7",
    "wof:placetype":"locality",
    "wof:population":115
},
  "geometry": {"coordinates":[33.05418,34.772461],"type":"Point"}
}