{
  "type": "Feature",
  "properties": {
    "iso:country":"CY",
    "name:deu_x_preferred":[
        "Petra"
    ],
    "name:ell_x_preferred":[
        "P\u00e9tra"
    ],
    "name:ell_x_variant":[
        "\u03a0\u03ad\u03c4\u03c1\u03b1",
        "\u03a0\u03ad\u03c4\u03c1\u03b1 \u03a3\u03bf\u03bb\u03ad\u03b1\u03c2",
        "\u03a4\u03ac\u03c3\u03ba\u03b9\u03bf\u03ca"
    ],
    "name:eng_x_preferred":[
        "Petra"
    ],
    "name:eng_x_variant":[
        "Dereli",
        "Petre"
    ],
    "name:fas_x_preferred":[
        "\u067e\u062a\u0631\u0627\u060c \u0642\u0628\u0631\u0633"
    ],
    "name:fas_x_variant":[
        "\u067e\u062a\u0631\u0627"
    ],
    "name:nld_x_preferred":[
        "Petra"
    ],
    "name:pol_x_preferred":[
        "Petra"
    ],
    "name:spa_x_preferred":[
        "Ta\u015fk\u00f6y"
    ],
    "name:tur_x_preferred":[
        "Ta\u015fk\u00f6y"
    ],
    "name:und_x_colloquial":[
        "Taskoey",
        "Taskoy"
    ],
    "name:und_x_variant":[
        "Ta\u015fk\u00f6y"
    ],
    "name:unk_x_variant":[
        "Ta\u015fk\u00f6y"
    ],
    "name:urd_x_preferred":[
        "\u067e\u06cc\u062a\u0631\u0627\u060c \u0642\u0628\u0631\u0635"
    ],
    "name:urd_x_variant":[
        "\u067e\u06cc\u062a\u0631\u0627"
    ],
    "qs:a0":"\u039a\u03cd\u03c0\u03c1\u03bf\u03c2",
    "qs:a1":"*\u039b\u03b5\u03c5\u03ba\u03c9\u03c3\u03af\u03b1",
    "qs:a1_alt":"Lefkosia",
    "qs:a1r":"0",
    "qs:adm0":"\u039a\u03cd\u03c0\u03c1\u03bf\u03c2",
    "qs:la_lc":"*",
    "qs:level":"locality",
    "qs:loc":"\u03a0\u03ad\u03c4\u03c1\u03b1",
    "qs:loc_alt":"Petra",
    "qs:pop":0,
    "qs:type":"buffered point",
    "wof:lang":[
        "eng"
    ],
    "wof:name":"\u03a0\u03ad\u03c4\u03c1\u03b1",
    "wof:placetype":"locality"
},
  "geometry": {"coordinates":[32.908669,35.109699],"type":"Point"}
}