{
  "type": "Feature",
  "properties": {
    "gn:admin1_code":"05",
    "gn:asciiname":"Troodos",
    "gn:country_code":"CY",
    "gn:dem":1721,
    "gn:feature_class":"P",
    "gn:feature_code":"PPL",
    "gn:name":"Tr\u00f3odos",
    "gn:population":0,
    "gn:timezone":"Asia/Nicosia",
    "iso:country":"CY",
    "name:ell_x_preferred":[
        "Tr\u00f3odos"
    ],
    "name:ell_x_variant":[
        "\u03a4\u03c1\u03cc\u03bf\u03b4\u03bf\u03c2"
    ],
    "name:und_x_variant":[
        "Camp Troodos",
        "Tr\u00f3\u00f6dhos Resort",
        "Trodos"
    ],
    "wof:name":"Troodos",
    "wof:placetype":"locality"
},
  "geometry": {"coordinates":[32.8805,34.92344],"type":"Point"}
}