{
  "type": "Feature",
  "properties": {
    "iso:country":"CY",
    "name:arz_x_preferred":[
        "\u0627\u0644\u0648\u062f\u0627"
    ],
    "name:bul_x_preferred":[
        "\u0410\u043b\u043e\u0434\u0430"
    ],
    "name:ell_x_preferred":[
        "Al\u00f3da"
    ],
    "name:ell_x_variant":[
        "\u0391\u03bb\u03cc\u03b4\u03b1",
        "\u0391\u03c4\u03bb\u03b9\u03bb\u03ac\u03c1"
    ],
    "name:eng_x_preferred":[
        "Altilar"
    ],
    "name:eng_x_variant":[
        "Aloda",
        "Alodha",
        "Atlilar"
    ],
    "name:fas_x_preferred":[
        "\u0627\u0644\u0648\u062f\u0627"
    ],
    "name:hye_x_preferred":[
        "\u0531\u056c\u0578\u0564\u0561"
    ],
    "name:ita_x_preferred":[
        "Aloda"
    ],
    "name:msa_x_preferred":[
        "Aloda"
    ],
    "name:nld_x_preferred":[
        "Aloda"
    ],
    "name:pol_x_preferred":[
        "Aloda"
    ],
    "name:tur_x_preferred":[
        "Atl\u0131lar"
    ],
    "name:und_x_variant":[
        "Aloa"
    ],
    "name:urd_x_preferred":[
        "\u0622\u0644\u0648\u062f\u0627"
    ],
    "qs:a0":"\u039a\u03cd\u03c0\u03c1\u03bf\u03c2",
    "qs:a1":"*\u0391\u03bc\u03bc\u03cc\u03c7\u03c9\u03c3\u03c4\u03bf\u03c2",
    "qs:a1_alt":"Ammochostos",
    "qs:a1r":"0",
    "qs:adm0":"\u039a\u03cd\u03c0\u03c1\u03bf\u03c2",
    "qs:la_lc":"*",
    "qs:level":"locality",
    "qs:loc":"\u0391\u03bb\u03cc\u03b4\u03b1",
    "qs:loc_alt":"Aloda",
    "qs:pop":0,
    "qs:type":"buffered point",
    "wof:lang":[
        "eng"
    ],
    "wof:name":"\u0391\u03bb\u03cc\u03b4\u03b1",
    "wof:placetype":"locality"
},
  "geometry": {"coordinates":[33.826687,35.211087],"type":"Point"}
}